qwak_sdk/__init__.py
qwak_sdk/cli.py
qwak_sdk/commands/__init__.py
qwak_sdk/commands/admin/__init__.py
qwak_sdk/commands/admin/admin_commands_group.py
qwak_sdk/commands/admin/apikeys/__init__.py
qwak_sdk/commands/admin/apikeys/api_keys_commands_group.py
qwak_sdk/commands/admin/apikeys/generate/__init__.py
qwak_sdk/commands/admin/apikeys/generate/_logic.py
qwak_sdk/commands/admin/apikeys/generate/ui.py
qwak_sdk/commands/admin/apikeys/revoke/__init__.py
qwak_sdk/commands/admin/apikeys/revoke/_logic.py
qwak_sdk/commands/admin/apikeys/revoke/ui.py
qwak_sdk/commands/audience/__init__.py
qwak_sdk/commands/audience/_logic/__init__.py
qwak_sdk/commands/audience/_logic/config/__init__.py
qwak_sdk/commands/audience/_logic/config/config_base.py
qwak_sdk/commands/audience/_logic/config/parser.py
qwak_sdk/commands/audience/_logic/config/v1/__init__.py
qwak_sdk/commands/audience/_logic/config/v1/audience_config.py
qwak_sdk/commands/audience/_logic/config/v1/conditions_config.py
qwak_sdk/commands/audience/_logic/config/v1/config_v1.py
qwak_sdk/commands/audience/_logic/config/v1/route_config.py
qwak_sdk/commands/audience/_logic/config/v1/spec.py
qwak_sdk/commands/auto_scalling/__init__.py
qwak_sdk/commands/auto_scalling/_logic/__init__.py
qwak_sdk/commands/auto_scalling/_logic/config/__init__.py
qwak_sdk/commands/auto_scalling/_logic/config/config.py
qwak_sdk/commands/auto_scalling/_logic/config/parser.py
qwak_sdk/commands/auto_scalling/attach/__init__.py
qwak_sdk/commands/auto_scalling/attach/_logic.py
qwak_sdk/commands/auto_scalling/attach/ui.py
qwak_sdk/commands/auto_scalling/autoscaling_commands_group.py
qwak_sdk/commands/automations/__init__.py
qwak_sdk/commands/automations/automations_commands_group.py
qwak_sdk/commands/automations/delete/__init__.py
qwak_sdk/commands/automations/delete/_logic.py
qwak_sdk/commands/automations/delete/ui.py
qwak_sdk/commands/automations/executions/__init__.py
qwak_sdk/commands/automations/executions/executions_commands_group.py
qwak_sdk-0.10.2.dist-info/entry_points.txt
qwak_sdk-0.10.2.dist-info/WHEEL
qwak_sdk-0.10.2.dist-info/METADATA
qwak_sdk-0.10.2.dist-info/RECORD
